{
  "persons": [
    {
      "name": "Bon",
      "number": "3434344",
      "id": 39
    },
    {
      "name": "Celia",
      "number": "44444",
      "id": 43
    },
    {
      "name": "Andy",
      "number": "1",
      "id": 44
    },
    {
      "name": "Bobby",
      "number": "2",
      "id": 45
    },
    {
      "name": "Derek",
      "number": "3",
      "id": 46
    },
    {
      "name": "Jim",
      "number": "8",
      "id": 47
    },
    {
      "name": "Arya",
      "number": "90",
      "id": 48
    }
  ]
}